{
  "trackers": [
    {
      "type": "unknown",
      "url": "https://oos.cloudgouv-eu-west-1.outscale.com/wagtail-zlv/images/logo_ZLV_header-website.original.svg?AWSAccessKeyId=IIABDQQ1TNOJM01L6ED9&Signature=yjRo1VpeIzRqV16FTef6j8pcShQ%3D&Expires=1726386910"
    },
    {
      "type": "unknown",
      "url": "https://oos.cloudgouv-eu-west-1.outscale.com/wagtail-zlv/images/photo_accueil_avant_apres.original.png?AWSAccessKeyId=IIABDQQ1TNOJM01L6ED9&Signature=jQ4Ie3gj5AySxpLrmrV62RwxhYo%3D&Expires=1726386910"
    },
    {
      "type": "unknown",
      "url": "https://oos.cloudgouv-eu-west-1.outscale.com/wagtail-zlv/images/statistic_chart.3b2a717c3bc810228dfb5eb49dc33b.width-800.svg?AWSAccessKeyId=IIABDQQ1TNOJM01L6ED9&Signature=PZkGNEBkaRFQVViyAPBWb5LUNHw%3D&Expires=1726386910"
    },
    {
      "type": "unknown",
      "url": "https://oos.cloudgouv-eu-west-1.outscale.com/wagtail-zlv/images/location_review.3855ea620bd4c595a77d087ceaae6f.width-800.svg?AWSAccessKeyId=IIABDQQ1TNOJM01L6ED9&Signature=S7alLjbU6NAkYPicDwLJwxyb6cM%3D&Expires=1726386910"
    },
    {
      "type": "unknown",
      "url": "https://oos.cloudgouv-eu-west-1.outscale.com/wagtail-zlv/images/collaboration.b7d540aec8cb66da8b0473eba30a6502.width-800.svg?AWSAccessKeyId=IIABDQQ1TNOJM01L6ED9&Signature=FgdTgR5cE3qJv%2Fklyr7pnwam1Po%3D&Expires=1726386910"
    },
    {
      "type": "unknown",
      "url": "https://oos.cloudgouv-eu-west-1.outscale.com/wagtail-zlv/images/real_time_collaboration.9f1e4e6abe5ea6c9fd17f9.width-800.svg?AWSAccessKeyId=IIABDQQ1TNOJM01L6ED9&Signature=hXWzblMCHGluV97QuNzWgdWZ8js%3D&Expires=1726386910"
    },
    {
      "type": "unknown",
      "url": "https://oos.cloudgouv-eu-west-1.outscale.com/wagtail-zlv/images/antonin-carvalho-Jq1u4OOfI0M-unsplash_1.width-1200.jpg?AWSAccessKeyId=IIABDQQ1TNOJM01L6ED9&Signature=ym0VLR3MskKppz6dzSqiMZShS8o%3D&Expires=1726386910"
    },
    {
      "type": "unknown",
      "url": "https://oos.cloudgouv-eu-west-1.outscale.com/wagtail-zlv/images/cecile-musy-TTEkReP50x4-unsplash_2_1.width-1200.jpg?AWSAccessKeyId=IIABDQQ1TNOJM01L6ED9&Signature=wJ3xeYzLcQRWLPdoDpOAapoVkus%3D&Expires=1726386910"
    },
    {
      "type": "unknown",
      "url": "https://oos.cloudgouv-eu-west-1.outscale.com/wagtail-zlv/images/pedro-lastra-XlSgaYMWsZ8-unsplash_1.width-1200.jpg?AWSAccessKeyId=IIABDQQ1TNOJM01L6ED9&Signature=tDoUN0XqQ%2F8bKdifrFQXQly0Q6k%3D&Expires=1726386910"
    },
    {
      "type": "unknown",
      "url": "https://oos.cloudgouv-eu-west-1.outscale.com/wagtail-zlv/images/LV_photo.width-1200.jpg?AWSAccessKeyId=IIABDQQ1TNOJM01L6ED9&Signature=xuSt5%2FbdeWoPBzw9vPPHMCRnVPw%3D&Expires=1726386910"
    },
    {
      "type": "unknown",
      "url": "https://oos.cloudgouv-eu-west-1.outscale.com/wagtail-zlv/images/roubaix_pp.original.png?AWSAccessKeyId=IIABDQQ1TNOJM01L6ED9&Signature=joY3reNcheh%2Bs8exAr7K3u6OcLc%3D&Expires=1726386910"
    },
    {
      "type": "unknown",
      "url": "https://oos.cloudgouv-eu-west-1.outscale.com/wagtail-zlv/images/strasbourg_pp.original.png?AWSAccessKeyId=IIABDQQ1TNOJM01L6ED9&Signature=Q73TdRVu9clm3FWpfH%2FxBtyXkuA%3D&Expires=1726386910"
    },
    {
      "type": "unknown",
      "url": "https://oos.cloudgouv-eu-west-1.outscale.com/wagtail-zlv/images/cahors_pp.original.png?AWSAccessKeyId=IIABDQQ1TNOJM01L6ED9&Signature=84JUDaMWcDfAWiLtlxzVDUXovAU%3D&Expires=1726386910"
    },
    {
      "type": "unknown",
      "url": "https://oos.cloudgouv-eu-west-1.outscale.com/wagtail-zlv/images/rennes_pp.original.png?AWSAccessKeyId=IIABDQQ1TNOJM01L6ED9&Signature=fDpgI9FG57pm5XrAPjJpOXT7pqI%3D&Expires=1726386910"
    },
    {
      "type": "unknown",
      "url": "https://oos.cloudgouv-eu-west-1.outscale.com/wagtail-zlv/images/Logo_CA_Chateauroux_Metropole.original.png?AWSAccessKeyId=IIABDQQ1TNOJM01L6ED9&Signature=PTFGVreMQj3FOIYR4w2Bm7pXAQ0%3D&Expires=1726386910"
    },
    {
      "type": "unknown",
      "url": "https://oos.cloudgouv-eu-west-1.outscale.com/wagtail-zlv/images/lyon_pp.original.png?AWSAccessKeyId=IIABDQQ1TNOJM01L6ED9&Signature=YB%2BoFutQO511Wk04b2QzO7IxsnQ%3D&Expires=1726386910"
    },
    {
      "type": "unknown",
      "url": "https://oos.cloudgouv-eu-west-1.outscale.com/wagtail-zlv/images/logo_saint_log_agglo.original.png?AWSAccessKeyId=IIABDQQ1TNOJM01L6ED9&Signature=yUvctKdZepbml9V0sk%2Fh9mAF%2B6k%3D&Expires=1726386910"
    },
    {
      "type": "unknown",
      "url": "https://oos.cloudgouv-eu-west-1.outscale.com/wagtail-zlv/images/Logo-CCKB-A.original.jpg?AWSAccessKeyId=IIABDQQ1TNOJM01L6ED9&Signature=Y2lE3CpViFqXKVdRAcB%2B8enKCD0%3D&Expires=1726386910"
    }
  ],
  "cookies": [],
  "headers": {
    "content-encoding": "gzip",
    "content-language": "fr",
    "content-type": "text/html; charset=utf-8",
    "cross-origin-opener-policy": "same-origin",
    "date": "Sun, 15 Sep 2024 06:55:10 GMT",
    "referrer-policy": "same-origin",
    "strict-transport-security": "max-age=31536000",
    "vary": "Accept-Language, Cookie",
    "x-content-type-options": "nosniff",
    "x-frame-options": "DENY",
    "x-request-id": "70c529e5-2965-48c8-ad56-0cf047afb169"
  },
  "endpoints": [
    {
      "hostname": "zerologementvacant.beta.gouv.fr",
      "ip": "109.232.236.90",
      "geoip": {
        "continent": {
          "code": "EU",
          "geoname_id": 6255148,
          "names": {
            "de": "Europa",
            "en": "Europe",
            "es": "Europa",
            "fr": "Europe",
            "ja": "ヨーロッパ",
            "pt-BR": "Europa",
            "ru": "Европа",
            "zh-CN": "欧洲"
          }
        },
        "country": {
          "geoname_id": 3017382,
          "is_in_european_union": true,
          "iso_code": "FR",
          "names": {
            "de": "Frankreich",
            "en": "France",
            "es": "Francia",
            "fr": "France",
            "ja": "フランス共和国",
            "pt-BR": "França",
            "ru": "Франция",
            "zh-CN": "法国"
          }
        },
        "location": {
          "accuracy_radius": 500,
          "latitude": 48.8582,
          "longitude": 2.3387,
          "time_zone": "Europe/Paris"
        },
        "registered_country": {
          "geoname_id": 3017382,
          "is_in_european_union": true,
          "iso_code": "FR",
          "names": {
            "de": "Frankreich",
            "en": "France",
            "es": "Francia",
            "fr": "France",
            "ja": "フランス共和国",
            "pt-BR": "França",
            "ru": "Франция",
            "zh-CN": "法国"
          }
        }
      }
    },
    {
      "hostname": "oos.cloudgouv-eu-west-1.outscale.com",
      "ip": "185.21.194.76",
      "geoip": {
        "continent": {
          "code": "EU",
          "geoname_id": 6255148,
          "names": {
            "de": "Europa",
            "en": "Europe",
            "es": "Europa",
            "fr": "Europe",
            "ja": "ヨーロッパ",
            "pt-BR": "Europa",
            "ru": "Европа",
            "zh-CN": "欧洲"
          }
        },
        "country": {
          "geoname_id": 3017382,
          "is_in_european_union": true,
          "iso_code": "FR",
          "names": {
            "de": "Frankreich",
            "en": "France",
            "es": "Francia",
            "fr": "France",
            "ja": "フランス共和国",
            "pt-BR": "França",
            "ru": "Франция",
            "zh-CN": "法国"
          }
        },
        "location": {
          "accuracy_radius": 500,
          "latitude": 48.8582,
          "longitude": 2.3387,
          "time_zone": "Europe/Paris"
        },
        "registered_country": {
          "geoname_id": 3017382,
          "is_in_european_union": true,
          "iso_code": "FR",
          "names": {
            "de": "Frankreich",
            "en": "France",
            "es": "Francia",
            "fr": "France",
            "ja": "フランス共和国",
            "pt-BR": "França",
            "ru": "Франция",
            "zh-CN": "法国"
          }
        }
      }
    }
  ]
}
