{"totalCount":5,"grade":"F","repositories":[{"url":"https://github.com/MTES-MCT/apilos","grade":"F","alerts":[{"number":17,"created_at":"2022-05-05T12:34:08Z","updated_at":"2022-07-04T15:19:20Z","url":"https://api.github.com/repos/MTES-MCT/apilos/code-scanning/alerts/17","html_url":"https://github.com/MTES-MCT/apilos/security/code-scanning/17","state":"open","fixed_at":null,"dismissed_by":null,"dismissed_at":null,"dismissed_reason":null,"dismissed_comment":null,"rule":{"id":"py/path-injection","severity":"error","description":"Uncontrolled data used in path expression","name":"py/path-injection","tags":["correctness","external/cwe/cwe-022","external/cwe/cwe-023","external/cwe/cwe-036","external/cwe/cwe-073","external/cwe/cwe-099","security"],"security_severity_level":"high"},"tool":{"name":"CodeQL","guid":null,"version":"2.9.4"},"most_recent_instance":{"ref":"refs/heads/develop","analysis_key":".github/workflows/codeql-analysis.yml:analyze","environment":"{\"language\":\"python\"}","category":".github/workflows/codeql-analysis.yml:analyze/language:python","state":"open","commit_sha":"7a96a5f22746d8742d70b4c33454ca9a2ac8f870","message":{"text":"This path depends on a user-provided value."},"location":{"path":"upload/views.py","start_line":70,"end_line":70,"start_column":33,"end_column":61},"classifications":[]},"instances_url":"https://api.github.com/repos/MTES-MCT/apilos/code-scanning/alerts/17/instances"},{"number":16,"created_at":"2022-05-05T12:34:08Z","updated_at":"2022-07-04T15:19:20Z","url":"https://api.github.com/repos/MTES-MCT/apilos/code-scanning/alerts/16","html_url":"https://github.com/MTES-MCT/apilos/security/code-scanning/16","state":"open","fixed_at":null,"dismissed_by":null,"dismissed_at":null,"dismissed_reason":null,"dismissed_comment":null,"rule":{"id":"py/path-injection","severity":"error","description":"Uncontrolled data used in path expression","name":"py/path-injection","tags":["correctness","external/cwe/cwe-022","external/cwe/cwe-023","external/cwe/cwe-036","external/cwe/cwe-073","external/cwe/cwe-099","security"],"security_severity_level":"high"},"tool":{"name":"CodeQL","guid":null,"version":"2.9.4"},"most_recent_instance":{"ref":"refs/heads/develop","analysis_key":".github/workflows/codeql-analysis.yml:analyze","environment":"{\"language\":\"python\"}","category":".github/workflows/codeql-analysis.yml:analyze/language:python","state":"open","commit_sha":"7a96a5f22746d8742d70b4c33454ca9a2ac8f870","message":{"text":"This path depends on a user-provided value."},"location":{"path":"upload/views.py","start_line":68,"end_line":68,"start_column":35,"end_column":63},"classifications":[]},"instances_url":"https://api.github.com/repos/MTES-MCT/apilos/code-scanning/alerts/16/instances"},{"number":13,"created_at":"2022-04-25T14:49:23Z","updated_at":"2022-07-04T15:18:30Z","url":"https://api.github.com/repos/MTES-MCT/apilos/code-scanning/alerts/13","html_url":"https://github.com/MTES-MCT/apilos/security/code-scanning/13","state":"open","fixed_at":null,"dismissed_by":null,"dismissed_at":null,"dismissed_reason":null,"dismissed_comment":null,"rule":{"id":"js/xss-through-dom","severity":"warning","description":"DOM text reinterpreted as HTML","name":"js/xss-through-dom","tags":["external/cwe/cwe-079","external/cwe/cwe-116","security"],"security_severity_level":"medium"},"tool":{"name":"CodeQL","guid":null,"version":"2.9.4"},"most_recent_instance":{"ref":"refs/heads/develop","analysis_key":".github/workflows/codeql-analysis.yml:analyze","environment":"{\"language\":\"javascript\"}","category":".github/workflows/codeql-analysis.yml:analyze/language:javascript","state":"open","commit_sha":"7a96a5f22746d8742d70b4c33454ca9a2ac8f870","message":{"text":"DOM text is reinterpreted as HTML without escaping meta-characters."},"location":{"path":"static/bootstrap/js/bootstrap.bundle.js","start_line":1076,"end_line":1076,"start_column":22,"end_column":30},"classifications":[]},"instances_url":"https://api.github.com/repos/MTES-MCT/apilos/code-scanning/alerts/13/instances"},{"number":12,"created_at":"2022-04-25T14:49:23Z","updated_at":"2022-07-04T15:18:30Z","url":"https://api.github.com/repos/MTES-MCT/apilos/code-scanning/alerts/12","html_url":"https://github.com/MTES-MCT/apilos/security/code-scanning/12","state":"open","fixed_at":null,"dismissed_by":null,"dismissed_at":null,"dismissed_reason":null,"dismissed_comment":null,"rule":{"id":"js/xss-through-dom","severity":"warning","description":"DOM text reinterpreted as HTML","name":"js/xss-through-dom","tags":["external/cwe/cwe-079","external/cwe/cwe-116","security"],"security_severity_level":"medium"},"tool":{"name":"CodeQL","guid":null,"version":"2.9.4"},"most_recent_instance":{"ref":"refs/heads/develop","analysis_key":".github/workflows/codeql-analysis.yml:analyze","environment":"{\"language\":\"javascript\"}","category":".github/workflows/codeql-analysis.yml:analyze/language:javascript","state":"open","commit_sha":"7a96a5f22746d8742d70b4c33454ca9a2ac8f870","message":{"text":"DOM text is reinterpreted as HTML without escaping meta-characters."},"location":{"path":"static/bootstrap/js/bootstrap.js","start_line":1077,"end_line":1077,"start_column":22,"end_column":30},"classifications":[]},"instances_url":"https://api.github.com/repos/MTES-MCT/apilos/code-scanning/alerts/12/instances"},{"number":11,"created_at":"2022-03-29T13:13:43Z","updated_at":"2022-07-04T15:18:30Z","url":"https://api.github.com/repos/MTES-MCT/apilos/code-scanning/alerts/11","html_url":"https://github.com/MTES-MCT/apilos/security/code-scanning/11","state":"open","fixed_at":null,"dismissed_by":null,"dismissed_at":null,"dismissed_reason":null,"dismissed_comment":null,"rule":{"id":"js/incomplete-sanitization","severity":"warning","description":"Incomplete string escaping or encoding","name":"js/incomplete-sanitization","tags":["correctness","external/cwe/cwe-020","external/cwe/cwe-080","external/cwe/cwe-116","security"],"security_severity_level":"high"},"tool":{"name":"CodeQL","guid":null,"version":"2.9.4"},"most_recent_instance":{"ref":"refs/heads/develop","analysis_key":".github/workflows/codeql-analysis.yml:analyze","environment":"{\"language\":\"javascript\"}","category":".github/workflows/codeql-analysis.yml:analyze/language:javascript","state":"open","commit_sha":"7a96a5f22746d8742d70b4c33454ca9a2ac8f870","message":{"text":"This replaces only the first occurrence of '\"'."},"location":{"path":"static/js/dropzone-client.js","start_line":46,"end_line":46,"start_column":28,"end_column":45},"classifications":[]},"instances_url":"https://api.github.com/repos/MTES-MCT/apilos/code-scanning/alerts/11/instances"}]}]}