{
  "id": "vigieau",
  "type": "startup",
  "attributes": {
    "name": "Vigieau",
    "pitch": "Faire évoluer les usagers vers des pratiques sobres de l’eau et respectueuses des mesures de restriction.",
    "link": "https://vigieau.gouv.fr/",
    "repository": "https://github.com/MTES-MCT/secheresse-front; ",
    "contact": "astrid.tarteret@beta.gouv.fr",
    "content_url_encoded_markdown": "%23%23%20Contexte%0A%0AL%E2%80%99ann%C3%A9e%202022%20a%20%C3%A9t%C3%A9%20marqu%C3%A9e%20par%20une%20s%C3%A9cheresse%20prolong%C3%A9e%2C%20intense%20et%20%C3%A9tendue.%20Le%20d%C3%A9but%20de%20l%E2%80%99ann%C3%A9e%202023%20a%20%C3%A9t%C3%A9%20marqu%C3%A9%20par%20une%20s%C3%A9cheresse%20hivernale%20avec%2032%20jours%20sans%20pr%C3%A9cipitations%E2%80%A6%0A%0AA%20l%E2%80%99%C3%A9t%C3%A9%202022%20%3A%0A%0A%2B110%0Abassins%20versant%20connaissent%20des%20tensions%20structurelles.%20%0A%0A93%0Ad%C3%A9partements%20ont%20connu%20des%20mesures%20de%20restrictions%20d%E2%80%99eau%0A%0A%2B1000%20%0Acommunes%20ont%20eu%20rupture%20d%E2%80%99approvisionnement%20en%20eau%20potable%0A%0A%E2%80%A6%20Or%2C%20ces%20tensions%20vont%20s%27accro%C3%AEtre%20avec%20le%20d%C3%A9r%C3%A8glement%20climatique%20et%20les%20cons%C3%A9quences%20sur%20la%20disponibilit%C3%A9%20et%20la%20qualit%C3%A9%20de%20la%20ressource%20en%20eau%20sont%20d%E2%80%99ores%20et%20d%C3%A9j%C3%A0%20de%20plus%20en%20plus%20visibles.%0A%0APour%20r%C3%A9pondre%20%C3%A0%20cette%20probl%C3%A9matique%2C%20l%E2%80%99Etat%20s%E2%80%99est%20outill%C3%A9%20depuis%202012%20d%E2%80%99une%20application%20de%20gestion%20des%20arr%C3%AAt%C3%A9s%20de%20restriction%20d%E2%80%99eau%20%3A%20Propluvia.%20N%C3%A9anmoins%2C%20l%27outil%20ne%20permet%20pas%20aux%20usagers%20de%20savoir%20quelles%20sont%20les%20restrictions%20qui%20les%20concernent%2C%20des%20difficult%C3%A9s%20d%27op%C3%A9rations%20majeures%20ont%20%C3%A9galement%20affect%C3%A9%20le%20site%20%C3%A0%20l%27%C3%A9t%C3%A9%202022%0A%0ALe%20premier%20chantier%20de%20la%20planification%20%C3%A9cologique%20r%C3%A9v%C3%A9l%C3%A9%20le%2030%20mars%202023%20vise%20une%20gestion%20sobre%20de%20la%20ressource%20afin%20de%20garantir%20de%20l%E2%80%99eau%20pour%20tous%2C%20de%20qualit%C3%A9%20et%20des%20%C3%A9cosyst%C3%A8mes%20pr%C3%A9serv%C3%A9s.%20Parmi%20les%20objectifs%20%3A%20mieux%20communiquer%20sur%20les%20restrictions%20en%20p%C3%A9riode%20de%20s%C3%A9cheresse%20via%20un%20%22Ecowatt%20de%20l%27Eau%22%20qui%20donne%20lieu%20%C3%A0%20Vigieau%20%0A%0A%23%23%20Probl%C3%A8me%0A%0AComment%20faire%20%C3%A9voluer%20les%20usagers%20vers%20des%20pratiques%20sobres%20de%20l%E2%80%99eau%20et%20respectueuses%20des%20mesures%20de%20restriction%20%3F%0A%0APrincipaux%20probl%C3%A8mes%20identifi%C3%A9s%20pour%20les%20DDTs%20%3A%20%0A%0A%5C-%EF%BB%BF%20Difficult%C3%A9%20pour%20les%20DDTs%20%C3%A0%20communiquer%20l%27information%20sur%20les%20restrictions%20aux%20particuliers%20et%20%C3%A0%20rendre%20cette%20information%20lisible.%20%20%0A%0A%5C-%EF%BB%BF%20Les%20DDTs%20perdent%20un%20temps%20significatif%20%C3%A0%20faire%20remonter%20l%27information%20des%20arr%C3%AAt%C3%A9s%20cadres%20et%20arr%C3%AAt%C3%A9s%20de%20restriction%20dans%20le%20back%20office%20existant%20%3A%20Propluvia%20Priv%C3%A9%2C%20il%20n%27est%20pas%20adapt%C3%A9%20%C3%A0%20leurs%20sp%C3%A9cificit%C3%A9s%20locales%20%0A%0A%5C-%EF%BB%BF%20Les%20DDTs%20prennent%20beaucoup%20de%20temps%20%C3%A0%20pr%C3%A9parer%20les%20comit%C3%A9s%20de%20ressource%20en%20eau%20et%20en%20particulier%20%C3%A0%20aggr%C3%A9ger%20les%20donn%C3%A9es%20sur%20l%27%C3%A9tat%20de%20la%20ressource%20en%20eau%20%28environ%201%20journ%C3%A9e%20par%20semaine%29%20%0A%0AP%EF%BB%BFrincipaux%20probl%C3%A8mes%20identifi%C3%A9s%20pour%20les%20particuliers%20%3A%20%0A%0A%5C-%EF%BB%BF%20Difficult%C3%A9%20%C3%A0%20comprendre%20la%20gravit%C3%A9%20sur%20l%27%C3%A9tat%20de%20la%20s%C3%A9cheresse%20et%20donc%20%C3%A0%20se%20sentir%20concern%C3%A9.%20Ils%20manquent%20d%27information%20pour%20quantifier%20le%20probl%C3%A8me%20%28ex%20%3A%20quelle%20est%20la%20situation%20des%20nappes%20et%20cours%20d%27eau%29%20%0A%0A%5C-%EF%BB%BF%20Difficult%C3%A9%20%C3%A0%20se%20positionner%20dans%20ce%20probl%C3%A8me%20%28ex%20%3A%20ils%20n%27ont%20aucune%20id%C3%A9e%20de%20leur%20consommation%20d%27eau%29%20%0A%0A%23%23%20Solution%0A%0AD%EF%BB%BFans%20un%20premier%20temps%2C%20cr%C3%A9ation%20d%27un%20outil%20permettant%20aux%20particuliers%20de%20%3A%20%0A%0A%5C-%EF%BB%BF%20conna%C3%AEtre%20les%20restrictions%20en%20vigueur%20sur%20leur%20territoire%0A%0A%5C-%EF%BB%BF%20mesurer%20leur%20consommation%20d%27eau%20%0A%0A%5C-%EF%BB%BF%20s%27informer%20sur%20les%20%C3%A9co-gestes%20%C3%A0%20adopter%20pour%20favoriser%20une%20consommation%20sobre%20de%20l%27eau%0A",
    "events": [
      {
        "name": "product_launch",
        "date": "2023-07-11",
        "comment": ""
      }
    ],
    "phases": [
      {
        "name": "investigation",
        "start": "2023-04-04",
        "end": ""
      }
    ]
  },
  "relationships": {
    "incubator": {
      "data": {
        "type": "incubator",
        "id": "mtes"
      }
    }
  }
}
