{
  "trackers": [
    {
      "type": "unknown",
      "url": "https://static.gitbook.com/_next/static/css/2e5af986969e6b64.css"
    },
    {
      "type": "unknown",
      "url": "https://static.gitbook.com/_next/static/css/b9d4de855d30ec1d.css"
    },
    {
      "type": "unknown",
      "url": "https://static.gitbook.com/_next/static/css/8a2fb91ea051f9c0.css"
    },
    {
      "type": "unknown",
      "url": "https://static.gitbook.com/_next/static/css/d93286a0a0a04830.css"
    },
    {
      "type": "unknown",
      "url": "https://static.gitbook.com/_next/static/chunks/webpack-7d9ce8436762e3fe.js"
    },
    {
      "type": "unknown",
      "url": "https://static.gitbook.com/_next/static/chunks/fd9d1056-ae64ba42edc9feae.js"
    },
    {
      "type": "unknown",
      "url": "https://static.gitbook.com/_next/static/chunks/8865-50f9eaec1ecf3d16.js"
    },
    {
      "type": "unknown",
      "url": "https://static.gitbook.com/_next/static/chunks/main-app-4a541b820797ccb8.js"
    },
    {
      "type": "unknown",
      "url": "https://static.gitbook.com/_next/static/chunks/app/global-error-c2a6089bea4c1665.js"
    },
    {
      "type": "unknown",
      "url": "https://static.gitbook.com/_next/static/chunks/f4e5f4e1-908bf29853b543b6.js"
    },
    {
      "type": "unknown",
      "url": "https://static.gitbook.com/_next/static/chunks/6769-908afa2c25414874.js"
    },
    {
      "type": "unknown",
      "url": "https://static.gitbook.com/_next/static/chunks/824-52ede7bc004284e5.js"
    },
    {
      "type": "unknown",
      "url": "https://static.gitbook.com/_next/static/chunks/app/(space)/layout-28d1ebe27b7fb908.js"
    },
    {
      "type": "unknown",
      "url": "https://static.gitbook.com/_next/static/chunks/app/(space)/error-81b9db2229accf37.js"
    },
    {
      "type": "unknown",
      "url": "https://static.gitbook.com/_next/static/chunks/7423-8979f58742c1c7e5.js"
    },
    {
      "type": "unknown",
      "url": "https://static.gitbook.com/_next/static/chunks/2610-255a9bfe36777431.js"
    },
    {
      "type": "unknown",
      "url": "https://static.gitbook.com/_next/static/chunks/5359-9c7fe417e4f5cb05.js"
    },
    {
      "type": "unknown",
      "url": "https://static.gitbook.com/_next/static/chunks/5361-fffc848bb4debd43.js"
    },
    {
      "type": "unknown",
      "url": "https://static.gitbook.com/_next/static/chunks/app/(space)/(content)/layout-335e75b08d95efac.js"
    },
    {
      "type": "unknown",
      "url": "https://static.gitbook.com/_next/static/chunks/app/(space)/(content)/%5B%5B...pathname%5D%5D/loading-b2ae363cbd704841.js"
    },
    {
      "type": "unknown",
      "url": "https://static.gitbook.com/_next/static/chunks/4355-c4b73c078d36ca57.js"
    },
    {
      "type": "unknown",
      "url": "https://static.gitbook.com/_next/static/chunks/1317-88becd8c934ac19b.js"
    },
    {
      "type": "unknown",
      "url": "https://static.gitbook.com/_next/static/chunks/9236-6e263ffcd310d824.js"
    },
    {
      "type": "unknown",
      "url": "https://static.gitbook.com/_next/static/chunks/app/(space)/(content)/%5B%5B...pathname%5D%5D/page-d740b4977a147f01.js"
    },
    {
      "type": "unknown",
      "url": "https://static.gitbook.com/_next/static/media/0e4fe491bf84089c-s.woff2"
    },
    {
      "type": "unknown",
      "url": "https://static.gitbook.com/_next/static/media/934c4b7cb736f2a3-s.woff2"
    },
    {
      "type": "unknown",
      "url": "https://static.gitbook.com/_next/static/media/0e4fe491bf84089c-s.woff2"
    },
    {
      "type": "unknown",
      "url": "https://static.gitbook.com/_next/static/media/934c4b7cb736f2a3-s.woff2"
    },
    {
      "type": "unknown",
      "url": "https://app.gitbook.com/__session?proposed=a8ac41ed-0298-4cfe-bf37-7543b90e4b0eR"
    },
    {
      "type": "unknown",
      "url": "https://api.gitbook.com/v1/orgs/-LM1SilvSmvp8Li_dl9_/sites/site_4IhAC/insights/track_view"
    },
    {
      "type": "unknown",
      "url": "https://api.gitbook.com/v1/orgs/-LM1SilvSmvp8Li_dl9_/sites/site_4IhAC/insights/track_view"
    }
  ],
  "cookies": [],
  "headers": {
    "age": "23",
    "alt-svc": "h3=\":443\"; ma=86400",
    "cache-control": "public, max-age=0, s-maxage=86340, stale-if-error=0",
    "cf-cache-status": "HIT",
    "cf-placement": "local-LAX",
    "cf-ray": "8a67e4228a1a7ee9-LAX",
    "content-encoding": "gzip",
    "content-security-policy": "default-src 'self' https://static.gitbook.com; script-src 'self' 'nonce-MmEzYmU0MGMtOWM2NS00M2FlLWE0OWEtMzk4OWU5N2E1OGE1' 'strict-dynamic' 'unsafe-inline' 'unsafe-eval' https://static.gitbook.com https://integrations.gitbook.com https://cdn.iframe.ly; style-src 'self' https://static.gitbook.com fonts.googleapis.com 'unsafe-inline'; img-src * 'self' blob: data: files.gitbook.com https://static.gitbook.com; connect-src * 'self' integrations.gitbook.com app.gitbook.com api.gitbook.com srv.buysellads.com https://static.gitbook.com; font-src 'self' fonts.gstatic.com https://static.gitbook.com; frame-src *; object-src 'none'; base-uri 'self' https://static.gitbook.com; form-action 'self' https://static.gitbook.com; frame-ancestors https:;",
    "content-type": "text/html; charset=utf-8",
    "date": "Sun, 21 Jul 2024 02:51:47 GMT",
    "last-modified": "Sun, 21 Jul 2024 02:51:23 GMT",
    "nel": "{\"success_fraction\":0,\"report_to\":\"cf-nel\",\"max_age\":604800}",
    "referrer-policy": "no-referrer-when-downgrade",
    "report-to": "{\"endpoints\":[{\"url\":\"https:\\/\\/a.nel.cloudflare.com\\/report\\/v4?s=oVnmEUZ1RLU30RSybkZySB65LX%2FWjPxL%2BsTA7wy57kjCUQafu2q4K5%2FacWvlSDQKtc2D%2FZEo8VtA7KUpDf2gOwUyVhoM0qIQDz8og28K0SxMFP%2BeyV25Ux3wRm27fMFjaMJPJ%2FjctohdAH1OII%2FD\"}],\"group\":\"cf-nel\",\"max_age\":604800}",
    "server": "cloudflare",
    "strict-transport-security": "max-age=31536000",
    "vary": "RSC, Next-Router-State-Tree, Next-Router-Prefetch, Next-Url, Accept-Encoding",
    "x-content-type-options": "nosniff",
    "x-edge-runtime": "1",
    "x-gitbook-cache": "hit",
    "x-gitbook-cache-tag": "release-10.9.802,site_4IhAC,site:site_4IhAC",
    "x-gitbook-version": "f6bacea",
    "x-matched-path": "/[[...pathname]]"
  },
  "endpoints": [
    {
      "hostname": "doc.covoiturage.beta.gouv.fr",
      "ip": "172.64.147.209",
      "geoip": {
        "registered_country": {
          "geoname_id": 6252001,
          "iso_code": "US",
          "names": {
            "de": "USA",
            "en": "United States",
            "es": "Estados Unidos",
            "fr": "États Unis",
            "ja": "アメリカ",
            "pt-BR": "EUA",
            "ru": "США",
            "zh-CN": "美国"
          }
        }
      }
    },
    {
      "hostname": "static.gitbook.com",
      "ip": "172.64.146.167",
      "geoip": {
        "registered_country": {
          "geoname_id": 6252001,
          "iso_code": "US",
          "names": {
            "de": "USA",
            "en": "United States",
            "es": "Estados Unidos",
            "fr": "États Unis",
            "ja": "アメリカ",
            "pt-BR": "EUA",
            "ru": "США",
            "zh-CN": "美国"
          }
        }
      }
    },
    {
      "hostname": "app.gitbook.com",
      "ip": "172.64.146.167",
      "geoip": {
        "registered_country": {
          "geoname_id": 6252001,
          "iso_code": "US",
          "names": {
            "de": "USA",
            "en": "United States",
            "es": "Estados Unidos",
            "fr": "États Unis",
            "ja": "アメリカ",
            "pt-BR": "EUA",
            "ru": "США",
            "zh-CN": "美国"
          }
        }
      }
    },
    {
      "hostname": "api.gitbook.com",
      "ip": "104.18.41.89",
      "geoip": {
        "registered_country": {
          "geoname_id": 6252001,
          "iso_code": "US",
          "names": {
            "de": "USA",
            "en": "United States",
            "es": "Estados Unidos",
            "fr": "États Unis",
            "ja": "アメリカ",
            "pt-BR": "EUA",
            "ru": "США",
            "zh-CN": "美国"
          }
        }
      }
    }
  ]
}
