{
  "trackers": [],
  "cookies": [
    {
      "name": "_pk_ses.196.d2cc",
      "value": "1",
      "domain": "wikicarbone.beta.gouv.fr",
      "path": "/",
      "expires": 1633433345,
      "size": 17,
      "httpOnly": false,
      "secure": false,
      "session": false,
      "sameSite": "Lax",
      "sameParty": false,
      "sourceScheme": "Secure",
      "sourcePort": 443
    },
    {
      "name": "_pk_id.196.d2cc",
      "value": "f5d030232811473c.1633431545.",
      "domain": "wikicarbone.beta.gouv.fr",
      "path": "/",
      "expires": 1667386745,
      "size": 43,
      "httpOnly": false,
      "secure": false,
      "session": false,
      "sameSite": "Lax",
      "sameParty": false,
      "sourceScheme": "Secure",
      "sourcePort": 443
    }
  ],
  "headers": {
    "server": "openresty",
    "date": "Tue, 05 Oct 2021 10:59:04 GMT",
    "content-type": "text/html; charset=utf-8",
    "content-length": "424",
    "x-request-id": "85b36801-efcc-4f06-a48c-a315f17f8db9",
    "permissions-policy": "interest-cohort=()",
    "last-modified": "Mon, 04 Oct 2021 21:51:19 GMT",
    "access-control-allow-origin": "*",
    "strict-transport-security": "max-age=31556952",
    "etag": "W/\"615b7757-2c7\"",
    "expires": "Tue, 05 Oct 2021 09:56:52 GMT",
    "cache-control": "max-age=600",
    "content-encoding": "gzip",
    "x-proxy-cache": "MISS",
    "x-github-request-id": "4078:62AE:2CB116:2E996A:615C1F0C",
    "accept-ranges": "bytes",
    "via": "1.1 varnish",
    "age": "107",
    "x-served-by": "cache-cdg20734-CDG",
    "x-cache": "HIT",
    "x-cache-hits": "1",
    "x-timer": "S1633431543.027358,VS0,VE1",
    "vary": "Accept-Encoding",
    "x-fastly-request-id": "7eedfae9340e8e30067ded8c752e0b32690df71a"
  },
  "endpoints": [
    {
      "hostname": "wikicarbone.beta.gouv.fr",
      "ip": "109.232.236.90",
      "geoip": {
        "continent": {
          "code": "EU",
          "geoname_id": 6255148,
          "names": {
            "de": "Europa",
            "en": "Europe",
            "es": "Europa",
            "fr": "Europe",
            "ja": "ヨーロッパ",
            "pt-BR": "Europa",
            "ru": "Европа",
            "zh-CN": "欧洲"
          }
        },
        "country": {
          "geoname_id": 3017382,
          "is_in_european_union": true,
          "iso_code": "FR",
          "names": {
            "de": "Frankreich",
            "en": "France",
            "es": "Francia",
            "fr": "France",
            "ja": "フランス共和国",
            "pt-BR": "França",
            "ru": "Франция",
            "zh-CN": "法国"
          }
        },
        "location": {
          "accuracy_radius": 500,
          "latitude": 48.8582,
          "longitude": 2.3387,
          "time_zone": "Europe/Paris"
        },
        "registered_country": {
          "geoname_id": 3017382,
          "is_in_european_union": true,
          "iso_code": "FR",
          "names": {
            "de": "Frankreich",
            "en": "France",
            "es": "Francia",
            "fr": "France",
            "ja": "フランス共和国",
            "pt-BR": "França",
            "ru": "Франция",
            "zh-CN": "法国"
          }
        }
      }
    }
  ]
}
