{"urls":{"https://www.ecologie.gouv.fr/":{"status":200},"https://www.ecologie.gouv.fr/mentions-legales":{"status":200},"https://www.ecologie.gouv.fr/a-la-une":{"status":200},"https://www.ecologie.gouv.fr/presse":{"status":200},"https://www.ecologie.gouv.fr/jnqa":{"status":200},"https://www.ecologie.gouv.fr/politiques-publiques":{"status":200}},"technologies":[{"slug":"drupal","name":"Drupal","confidence":100,"version":"8","icon":"Drupal.svg","website":"https://drupal.org","cpe":"cpe:/a:drupal:drupal","categories":[{"id":1,"slug":"cms","name":"CMS"}]},{"slug":"php","name":"PHP","confidence":100,"version":null,"icon":"PHP.svg","website":"http://php.net","cpe":"cpe:/a:php:php","categories":[{"id":27,"slug":"programming-languages","name":"Programming languages"}]},{"slug":"chart-js","name":"Chart.js","confidence":100,"version":"2.7.1","icon":"Chart.js.svg","website":"https://www.chartjs.org","cpe":null,"categories":[{"id":25,"slug":"javascript-graphics","name":"JavaScript graphics"}]},{"slug":"zurb-foundation","name":"ZURB Foundation","confidence":100,"version":"6.5.3","icon":"ZURB Foundation.png","website":"http://foundation.zurb.com","cpe":null,"categories":[{"id":66,"slug":"ui-frameworks","name":"UI frameworks"}]},{"slug":"nginx","name":"Nginx","confidence":100,"version":null,"icon":"Nginx.svg","website":"http://nginx.org/en","cpe":"cpe:/a:nginx:nginx","categories":[{"id":22,"slug":"web-servers","name":"Web servers"},{"id":64,"slug":"reverse-proxies","name":"Reverse proxies"}]},{"slug":"slick","name":"Slick","confidence":100,"version":"1.6.0","icon":"default.svg","website":"https://kenwheeler.github.io/slick","cpe":null,"categories":[{"id":59,"slug":"javascript-libraries","name":"JavaScript libraries"}]},{"slug":"jsdelivr","name":"jsDelivr","confidence":100,"version":null,"icon":"jsdelivr-icon.svg","website":"https://www.jsdelivr.com/","cpe":null,"categories":[{"id":31,"slug":"cdn","name":"CDN"}]},{"slug":"twitter","name":"Twitter","confidence":100,"version":null,"icon":"Twitter.svg","website":"http://twitter.com","cpe":null,"categories":[{"id":5,"slug":"widgets","name":"Widgets"}]},{"slug":"mailchimp","name":"MailChimp","confidence":100,"version":null,"icon":"mailchimp.svg","website":"http://mailchimp.com","cpe":"cpe:/a:thinkshout:mailchimp","categories":[{"id":32,"slug":"marketing-automation","name":"Marketing automation"},{"id":75,"slug":"email","name":"Email"}]},{"slug":"twitter-ads","name":"Twitter Ads","confidence":100,"version":null,"icon":"Twitter.svg","website":"https://ads.twitter.com","cpe":null,"categories":[{"id":36,"slug":"advertising","name":"Advertising"}]},{"slug":"periodic","name":"Periodic","confidence":100,"version":null,"icon":"Periodic.svg","website":"https://periodic.is","cpe":null,"categories":[{"id":72,"slug":"appointment-scheduling","name":"Appointment scheduling"}]},{"slug":"jquery-ui","name":"jQuery UI","confidence":100,"version":"1.12.1","icon":"jQuery UI.svg","website":"http://jqueryui.com","cpe":"cpe:/a:jquery:jquery_ui","categories":[{"id":59,"slug":"javascript-libraries","name":"JavaScript libraries"}]},{"slug":"jquery","name":"jQuery","confidence":100,"version":"3.4.1","icon":"jQuery.svg","website":"https://jquery.com","cpe":"cpe:/a:jquery:jquery","categories":[{"id":59,"slug":"javascript-libraries","name":"JavaScript libraries"}]},{"slug":"at-internet-analyzer","name":"AT Internet Analyzer","confidence":100,"version":null,"icon":"AT Internet.png","website":"http://atinternet.com/en","cpe":null,"categories":[{"id":10,"slug":"analytics","name":"Analytics"}]}]}
